nattka/__init__.py
nattka/__main__.py
nattka/bugzilla.py
nattka/depgraph.py
nattka/git.py
nattka/keyword.py
nattka/package.py
nattka-0.4.2.data/data/share/bash-completion/completions/nattka
nattka-0.4.2.dist-info/entry_points.txt
nattka-0.4.2.dist-info/COPYING
nattka-0.4.2.dist-info/WHEEL
nattka-0.4.2.dist-info/METADATA
nattka-0.4.2.dist-info/RECORD
