Metadata-Version: 2.1
Name: nattka
Version: 0.4.2
Summary: A New Arch Tester Toolkit
Author-email: Michał Górny <mgorny@gentoo.org>
Requires-Python: >=3.10
Classifier: Development Status :: 5 - Production/Stable
Classifier: Environment :: Console
Classifier: Environment :: No Input/Output (Daemon)
Classifier: Intended Audience :: System Administrators
Classifier: License :: OSI Approved :: GNU General Public License v2 or later (GPLv2+)
Classifier: Operating System :: POSIX
Classifier: Programming Language :: Python :: 3 :: Only
Classifier: Topic :: Software Development :: Testing
Requires-Dist: lxml
Requires-Dist: pkgcheck
Requires-Dist: pkgcore
Requires-Dist: requests
Requires-Dist: snakeoil
Requires-Dist: networkx ; extra == "depgraph"
Requires-Dist: pytest ; extra == "test"
Requires-Dist: vcrpy ; extra == "test"
Project-URL: Homepage, https://github.com/mgorny/nattka/
Provides-Extra: depgraph
Provides-Extra: test
